synthetic_combinations/__init__.py
synthetic_combinations/synthetic_combinations.py
synthetic_combinations-0.0.2.dist-info/LICENSE
synthetic_combinations-0.0.2.dist-info/METADATA
synthetic_combinations-0.0.2.dist-info/WHEEL
synthetic_combinations-0.0.2.dist-info/top_level.txt
synthetic_combinations-0.0.2.dist-info/RECORD
